cs/lex.py
cs_lex-20250914.dist-info/WHEEL
cs_lex-20250914.dist-info/METADATA
cs_lex-20250914.dist-info/RECORD
