Metadata-Version: 2.4
Name: cs-lex
Version: 20250914
Summary: Lexical analysis functions, tokenisers, transcribers: an arbitrary assortment of lexical and tokenisation functions useful for writing recursive descent parsers, of which I have several. There are also some transcription functions for producing text from various objects, such as `hexify` and `unctrl`.
Keywords: python3
Author-email: Cameron Simpson <cs@cskk.id.au>
Classifier: Programming Language :: Python
Classifier: Programming Language :: Python :: 3
Classifier: Topic :: Text Processing
Classifier: Development Status :: 4 - Beta
Classifier: Intended Audience :: Developers
Classifier: Operating System :: OS Independent
Classifier: License :: OSI Approved :: GNU General Public License v3 or later (GPLv3+)
Requires-Dist: cs.dateutils>=20250724
Requires-Dist: cs.deco>=20250914
Requires-Dist: cs.gimmicks>=20250428
Requires-Dist: cs.obj>=20250306
Requires-Dist: cs.pfx>=20250914
Requires-Dist: cs.py.func>=20250914
Requires-Dist: cs.seq>=20200914
Requires-Dist: icontract
Requires-Dist: python-dateutil
Requires-Dist: typeguard
Project-URL: MonoRepo Commits, https://bitbucket.org/cameron_simpson/css/commits/branch/main
Project-URL: Monorepo Git Mirror, https://github.com/cameron-simpson/css
Project-URL: Monorepo Hg/Mercurial Mirror, https://hg.sr.ht/~cameron-simpson/css
Project-URL: Source, https://github.com/cameron-simpson/css/blob/main/lib/python/cs/lex.py
